Workbook

Sheet COVER
A1: ESTIMATED TAX WORKPAPER — ESTATE / TRUST (Form 1041)
A2: RAG Tax AI — CPA Firm Estimated Tax Template
A4: Client Name:
A5: Tax Year:
A6: Quarter / Period: | B6: Q1 / Q2 / Q3 / Q4 / Annual
A7: Data Through:
A8: Return Type: | B8: Form 1041
A9: State(s):
A10: Preparer:
A11: Date Prepared:
A13: LEGEND
A14: Blue cells | B14: INPUT — enter data here
A15: Yellow background | B15: INPUT — enter data here
A16: Green background | B16: RESULT — do not edit
A17: Light gray | B17: FORMULA / calculated
A18: Red background | B18: BALANCE DUE — payment required
A20: SHEET GUIDE
A21: COVER | B21: This sheet — client info and instructions
A22: P&L INPUT | B22: Enter YTD financial data — auto-annualizes
A23: BOOK-TO-TAX | B23: Book-to-tax reconciliation — meals, depreciation, etc.
A24: TAX CALC | B24: Federal and state tax computation
A25: PAYMENTS | B25: Prior payments, safe harbor, balance due
A26: SUMMARY | B26: Final output — amounts to pay and due dates

Sheet P&L INPUT
A1: PROFIT & LOSS — YTD INPUT & ANNUALIZATION
A2: Enter YTD amounts in column B (blue). Column C auto-annualizes. Enter actual months in B3 — this drives the annualization factor.
A3: ANNUALIZATION SETUP | C3: YTD Months | D3: Factor
A4: Months covered by P&L (enter number) | C4: 4 | D4: ← CHANGE THIS
A5: Annualization Factor (12 ÷ months) | C5: =IFERROR(12/C4,"-") -> 3
A7: ACCOUNT | B7: YTD Amount | C7: Annualized | E7: Source / Notes
A8: INCOME
A9: Gross Revenue / Sales | C9: =IF(B9="","-",B9*C5) -> -
A10: Other Operating Income | C10: =IF(B10="","-",B10*C5) -> -
A11: Interest Income | C11: =IF(B11="","-",B11*C5) -> -
A12: Other Income | C12: =IF(B12="","-",B12*C5) -> -
A13: TOTAL INCOME | C13: =SUM(C9:C12) -> 0
A15: OPERATING EXPENSES
A16: Officer / Owner Compensation | C16: =IF(B16="","-",B16*C5) -> -
A17: Salaries & Wages (non-officer) | C17: =IF(B17="","-",B17*C5) -> -
A18: Payroll Taxes | C18: =IF(B18="","-",B18*C5) -> -
A19: Rent / Lease | C19: =IF(B19="","-",B19*C5) -> -
A20: Utilities | C20: =IF(B20="","-",B20*C5) -> -
A21: Telephone & Internet | C21: =IF(B21="","-",B21*C5) -> -
A22: Office Supplies | C22: =IF(B22="","-",B22*C5) -> -
A23: Meals & Entertainment | C23: =IF(B23="","-",B23*C5) -> -
A24: Travel | C24: =IF(B24="","-",B24*C5) -> -
A25: Advertising & Marketing | C25: =IF(B25="","-",B25*C5) -> -
A26: Professional Fees | C26: =IF(B26="","-",B26*C5) -> -
A27: Insurance | C27: =IF(B27="","-",B27*C5) -> -
A28: Repairs & Maintenance | C28: =IF(B28="","-",B28*C5) -> -
A29: Depreciation (book) | C29: =IF(B29="","-",B29*C5) -> -
A30: Amortization | C30: =IF(B30="","-",B30*C5) -> -
A31: Interest Expense | C31: =IF(B31="","-",B31*C5) -> -
A32: Bank Charges | C32: =IF(B32="","-",B32*C5) -> -
A33: Other Deductions 1 | C33: =IF(B33="","-",B33*C5) -> -
A34: Other Deductions 2 | C34: =IF(B34="","-",B34*C5) -> -
A35: Other Deductions 3 | C35: =IF(B35="","-",B35*C5) -> -
A36: TOTAL EXPENSES | C36: =SUM(C16:C35) -> 0
A37: NET INCOME PER BOOKS (Annualized) | C37: =C13-C36 -> 0
A39: NET INCOME cell C37 feeds into BOOK-TO-TAX sheet automatically. Named range: net_income_ann

Sheet BS (IF NEEDED)
A1: BALANCE SHEET INPUT — USE ONLY IF NEEDED
A2: This sheet is OPTIONAL. Use it only when: (1) there are new fixed asset additions requiring depreciation analysis, or (2) large loans were taken that affect interest expense, or (3) equity changed unexpectedly.
A4: ITEM | B4: Prior Year End | C4: Current Period | D4: Change | E4: Action Required
A5: FIXED ASSETS — IDENTIFY NEW ADDITIONS
A6: Gross Fixed Assets (total cost) | D6: =IFERROR(C6-B6, "-") -> 0 | E6: Increase = new additions
A7: Less: Accumulated Depreciation | D7: =IFERROR(C7-B7, "-") -> 0
A8: Net Fixed Assets | D8: =IFERROR(C8-B8, "-") -> 0
A9: New Fixed Asset Additions (current period) | D9: =IFERROR(C9-B9, "-") -> 0 | E9: change in gross fixed assets
A10: Asset type (describe) | D10: =IFERROR(C10-B10, "-") -> 0 | E10: e.g. equipment, vehicle, leasehold
A11: Date placed in service | D11: =IFERROR(C11-B11, "-") -> 0 | E11: For bonus / §179 eligibility
A12: §179 Election Amount | D12: =IFERROR(C12-B12, "-") -> 0 | E12: Up to $1,250,000 for 2025
A13: Bonus Depreciation (40% of remaining basis for 2025) | D13: =IFERROR(C13-B13, "-") -> 0 | E13: IRC §168(k)
A14: MACRS Depreciation on remainder | D14: =IFERROR(C14-B14, "-") -> 0
A16: LOANS & DEBT — CHECK FOR INTEREST EXPENSE CHANGES
A17: Total Debt / Loans Payable | D17: =IFERROR(C17-B17, "-") -> 0
A18: New Loans This Period | D18: =IFERROR(C18-B18, "-") -> 0
A19: Loan Repayments | D19: =IFERROR(C19-B19, "-") -> 0

Sheet BOOK-TO-TAX
A1: BOOK-TO-TAX RECONCILIATION
A2: This sheet adjusts book net income to taxable income. Enter adjustments in column B. Column C shows the running total.
A4: LINE ITEM | B4: Amount | C4: Running Taxable Income | E4: Authority / Explanation
A5: Net Income per Books (from P&L INPUT) | B5: ='P&L INPUT'!C37 -> 0 | C5: =B5 -> 0
A7: ADD BACKS (Non-deductible items — increase taxable income)
A8: Meals & Entertainment — 50% disallowance | C8: =C7+B8 -> 0
A9: Entertainment (100% disallowed post-TCJA) | C9: =C8+B9 -> 0
A10: Political Contributions | C10: =C9+B10 -> 0
A11: Fines & Penalties | C11: =C10+B11 -> 0
A12: Life Insurance Premiums (officer, company beneficiary) | C12: =C11+B12 -> 0
A13: Federal Income Tax (1120 only) | C13: =C12+B13 -> 0
A14: Non-deductible Other (describe in notes) | C14: =C13+B14 -> 0
A16: DEDUCTIONS (Tax-only items — reduce taxable income)
A17: Depreciation — timing difference (book vs tax) | C17: =C16+B17 -> 0
A18: Section 179 Expensing (current year elections) | C18: =C17+B18 -> 0
A19: Bonus Depreciation (40% for 2025 QP) | C19: =C18+B19 -> 0
A20: Depletion (if applicable) | C20: =C19+B20 -> 0
A21: Tax-deductible Other (describe in notes) | C21: =C20+B21 -> 0
A23: CARRYFORWARDS
A24: Net Operating Loss (NOL) Carryforward | C24: =C23+B24 -> 0
A25: Capital Loss Carryforward | C25: =C24+B25 -> 0
A26: Charitable Contribution Carryforward | C26: =C25+B26 -> 0
A28: §163(j) BUSINESS INTEREST LIMITATION (if applicable)
A29: Only applies if business interest expense > floor amount. Enter disallowed amount as POSITIVE (adds back to taxable income).
A30: §163(j) Disallowed Interest Add-back | C30: =C29+B30 -> 0
A32: ESTIMATED ANNUALIZED TAXABLE INCOME | C32: =C31 -> 0
A33: This amount in C32 feeds into TAX CALC sheet.

Sheet TAX CALC
A1: FEDERAL & STATE TAX COMPUTATION — TAX YEAR 2025
A2: Taxable income flows from BOOK-TO-TAX sheet. Select filing status (1040) and verify rates for the tax year.
A4: INCOME BASE | B4: Amount | E4: Notes
A5: Annualized Taxable Income (from BOOK-TO-TAX) | B5: ='BOOK-TO-TAX'!C32 -> 0
A7: PASS-THROUGH ENTITY — TAX AT OWNER LEVEL
A8: For partnerships and S-corps, federal income tax is paid by owners, not the entity. Complete the 1040 template for each owner. This sheet calculates entity-level items only.
A9: Ordinary Business Income (pass-through) | B9: ='BOOK-TO-TAX'!C32 -> 0
A10: Owner 1 — Ownership % | C10: Enter as decimal e.g. 0.50 for 50%
A11: Owner 1 — Pass-through income | B11: =B9*B10 -> 0
A12: Owner 2 — Ownership % | C12: Enter as decimal; leave blank if single owner
A13: Owner 2 — Pass-through income | B13: =B9*B12 -> 0
A15: Use separate 1040 Estimated Tax Template for each owner to compute their personal federal tax.
A16: Entity Federal Tax Due (enter from owner templates)
A19: STATE TAX COMPUTATION
A20: Enter state tax rate and any state modifications below. Many states do NOT conform to federal bonus depreciation — verify.
A21: State | B21: NY
A22: State Tax Rate | B22: 0.0685
A23: State Modifications (add-backs — e.g. bonus depr add-back) | C23: Enter positive to add back; enter federal bonus depr as positive if state doesn't conform
A24: State Modifications (deductions — e.g. state NOL) | C24: Enter as NEGATIVE
A25: State Taxable Income | B25: =B5+B23+B24 -> 0
A26: State Tax (before credits) | B26: =IF(B25>0,B25*B22,0) -> 0
A27: State Credits (enter as NEGATIVE)
A28: PTE Tax (Pass-Through Entity Tax — enter if electing) | C28: State-level PTE election; deductible for federal purposes (SALT workaround)
A29: NET STATE TAX (Annual) | C29: =B26+B27+B28 -> 0
A31: Fed tax (C16) and State tax row feed into PAYMENTS sheet.

Sheet PAYMENTS
A1: ESTIMATED TAX — PAYMENTS & SAFE HARBOR ANALYSIS
A2: Enter prior payments in BLUE cells. Safe harbor and balance due are calculated automatically.
A4: PRIOR YEAR DATA (for safe harbor Option 2) | B4: Federal | C4: State | E4: Source
A5: Prior Year Total Tax (from prior year return) | C5: From 1040 Line 24 / 1120 Line 31 / 1120-S Sch K
A6: Prior year AGI (individuals — for 110% rule) | E6: If AGI > $150,000, use 110% of prior year tax for Option 2 (IRC §6654(d)(1)(B))
A8: SAFE HARBOR ANALYSIS | B8: Federal | C8: State
A9: Estimated Current Year Tax | B9: ='TAX CALC'!B16 -> 0 | C9: ='TAX CALC'!B29 -> 0
A10: Option 1 — 90% of current year tax (IRC §6654) | B10: =B9*0.9 -> 0 | C10: =C9*0.9 -> 0
A11: Option 2 — 100%/110% of prior year tax | B11: =IF(B6>150000,B5*1.1,B5*1) -> 0 | C11: =C5 -> From 1040 Line 24 / 1120 Line 31 / 1120-S Sch K
A12: RECOMMENDED SAFE HARBOR (lesser of Option 1 & 2) | B12: =IF(B11=0,B10,MIN(B10,B11)) -> 0 | C12: =IF(C11=0,C10,MIN(C10,C11)) -> 0
A14: PAYMENTS ALREADY MADE | B14: Federal | C14: State
A15: Q1 Estimated Tax Paid
A16: Q2 Estimated Tax Paid
A17: Q3 Estimated Tax Paid
A18: Extension Payment Made
A19: Overpayment from Prior Year Applied
A20: PTE Tax Credit (from state PTE election) | E20: State PTE creates federal deduction
A21: W-2 / Withholding (if applicable) | E21: 1040: enter total W-2 federal withholding here
A22: TOTAL PAYMENTS TO DATE | B22: =SUM(B15:B21) -> 0 | C22: =SUM(C15:C21) -> 0
A24: QUARTERLY BALANCE DUE | B24: Federal | C24: State | E24: Due Dates
A25: Q1 — 25% required (April 15) | B25: =MAX(0,B12*0.25-B22) -> 0 | C25: =MAX(0,C12*0.25-C22) -> 0 | E25: 2025-04-15
A26: Q2 — 50% required (June 15) | B26: =MAX(0,B12*0.5-B22) -> 0 | C26: =MAX(0,C12*0.5-C22) -> 0 | E26: 2025-06-15
A27: Q3 — 75% required (Sept 15) | B27: =MAX(0,B12*0.75-B22) -> 0 | C27: =MAX(0,C12*0.75-C22) -> 0 | E27: 2025-09-15
A28: Q4 — 100% required (Jan 15) | B28: =MAX(0,B12*1-B22) -> 0 | C28: =MAX(0,C12*1-C22) -> 0 | E28: 2026-01-15

Sheet SUMMARY
A1: ESTIMATED TAX SUMMARY — AMOUNTS DUE
A3: This summary is READ-ONLY. All amounts pull from other sheets.
A5: ITEM | B5: Federal | C5: State | D5: Total | E5: Due Date | F5: Pay At
A6: NOTE: Summary amounts reference PAYMENTS sheet rows 27-30. Verify row references match your actual PAYMENTS sheet after all data is entered.
A8: Annual Estimated Federal Tax | E8: Pull from TAX CALC sheet
A9: Safe Harbor Used
A11: PAYMENT INSTRUCTIONS — Federal: Pay at https://directpay.irs.gov | Select: Estimated Tax | Form 1040-ES or 1120-W | Tax Year
A12: State payments: Go to your state revenue department portal. CA: ftb.ca.gov | NY: tax.ny.gov | TX: No income tax | FL: floridarevenue.com (corps only) | Check state portal for your state.
